<?xml version="1.0" encoding="UTF-8" standalone="yes"?>
<?xml-stylesheet type="text/xsl" href="pedidos_admin.xsl"?>
<pedidos xmlns:xsi="http://www.w3.org/2001/XMLSchema-instance">
	<pedido>
		<id>1</id>
		<id_cliente>3</id_cliente>
		<fecha>02/28/2019</fecha>
	</pedido>
	<pedido>
		<id>2</id>
		<id_cliente>16</id_cliente>
		<fecha>04/13/2020</fecha>
	</pedido>
	<pedido>
		<id>3</id>
		<id_cliente>22</id_cliente>
		<fecha>07/16/2019</fecha>
	</pedido>
	<pedido>
		<id>4</id>
		<id_cliente>24</id_cliente>
		<fecha>03/26/2019</fecha>
	</pedido>
	<pedido>
		<id>5</id>
		<id_cliente>23</id_cliente>
		<fecha>06/12/2019</fecha>
	</pedido>
	<pedido>
		<id>6</id>
		<id_cliente>9</id_cliente>
		<fecha>09/23/2019</fecha>
	</pedido>
	<pedido>
		<id>7</id>
		<id_cliente>2</id_cliente>
		<fecha>03/26/2020</fecha>
	</pedido>
	<pedido>
		<id>8</id>
		<id_cliente>24</id_cliente>
		<fecha>05/19/2019</fecha>
	</pedido>
	<pedido>
		<id>9</id>
		<id_cliente>13</id_cliente>
		<fecha>07/09/2019</fecha>
	</pedido>
	<pedido>
		<id>10</id>
		<id_cliente>15</id_cliente>
		<fecha>08/20/2019</fecha>
	</pedido>
	<pedido>
		<id>11</id>
		<id_cliente>14</id_cliente>
		<fecha>05/09/2019</fecha>
	</pedido>
	<pedido>
		<id>12</id>
		<id_cliente>17</id_cliente>
		<fecha>04/14/2019</fecha>
	</pedido>
	<pedido>
		<id>13</id>
		<id_cliente>13</id_cliente>
		<fecha>12/14/2019</fecha>
	</pedido>
	<pedido>
		<id>14</id>
		<id_cliente>18</id_cliente>
		<fecha>10/08/2018</fecha>
	</pedido>
	<pedido>
		<id>15</id>
		<id_cliente>7</id_cliente>
		<fecha>05/17/2019</fecha>
	</pedido>
	<pedido>
		<id>16</id>
		<id_cliente>23</id_cliente>
		<fecha>01/26/2019</fecha>
	</pedido>
	<pedido>
		<id>17</id>
		<id_cliente>12</id_cliente>
		<fecha>10/28/2019</fecha>
	</pedido>
	<pedido>
		<id>18</id>
		<id_cliente>18</id_cliente>
		<fecha>11/29/2018</fecha>
	</pedido>
	<pedido>
		<id>19</id>
		<id_cliente>12</id_cliente>
		<fecha>05/12/2020</fecha>
	</pedido>
	<pedido>
		<id>20</id>
		<id_cliente>11</id_cliente>
		<fecha>11/19/2019</fecha>
	</pedido>
	<pedido>
		<id>21</id>
		<id_cliente>9</id_cliente>
		<fecha>06/21/2018</fecha>
	</pedido>
	<pedido>
		<id>22</id>
		<id_cliente>25</id_cliente>
		<fecha>01/14/2019</fecha>
	</pedido>
	<pedido>
		<id>23</id>
		<id_cliente>22</id_cliente>
		<fecha>11/09/2018</fecha>
	</pedido>
	<pedido>
		<id>24</id>
		<id_cliente>16</id_cliente>
		<fecha>08/22/2018</fecha>
	</pedido>
	<pedido>
		<id>25</id>
		<id_cliente>9</id_cliente>
		<fecha>01/22/2020</fecha>
	</pedido>
	<pedido>
		<id>26</id>
		<id_cliente>2</id_cliente>
		<fecha>10/03/2018</fecha>
	</pedido>
	<pedido>
		<id>27</id>
		<id_cliente>8</id_cliente>
		<fecha>12/29/2019</fecha>
	</pedido>
	<pedido>
		<id>28</id>
		<id_cliente>19</id_cliente>
		<fecha>08/16/2018</fecha>
	</pedido>
	<pedido>
		<id>29</id>
		<id_cliente>12</id_cliente>
		<fecha>11/04/2019</fecha>
	</pedido>
	<pedido>
		<id>30</id>
		<id_cliente>24</id_cliente>
		<fecha>01/22/2020</fecha>
	</pedido>
	<pedido>
		<id>31</id>
		<id_cliente>11</id_cliente>
		<fecha>11/20/2018</fecha>
	</pedido>
	<pedido>
		<id>32</id>
		<id_cliente>22</id_cliente>
		<fecha>08/17/2018</fecha>
	</pedido>
	<pedido>
		<id>33</id>
		<id_cliente>21</id_cliente>
		<fecha>06/27/2018</fecha>
	</pedido>
	<pedido>
		<id>34</id>
		<id_cliente>10</id_cliente>
		<fecha>05/22/2019</fecha>
	</pedido>
	<pedido>
		<id>35</id>
		<id_cliente>12</id_cliente>
		<fecha>09/26/2019</fecha>
	</pedido>
	<pedido>
		<id>36</id>
		<id_cliente>14</id_cliente>
		<fecha>11/16/2019</fecha>
	</pedido>
	<pedido>
		<id>37</id>
		<id_cliente>2</id_cliente>
		<fecha>03/27/2020</fecha>
	</pedido>
	<pedido>
		<id>38</id>
		<id_cliente>19</id_cliente>
		<fecha>10/06/2019</fecha>
	</pedido>
	<pedido>
		<id>39</id>
		<id_cliente>9</id_cliente>
		<fecha>01/17/2019</fecha>
	</pedido>
	<pedido>
		<id>40</id>
		<id_cliente>23</id_cliente>
		<fecha>12/28/2018</fecha>
	</pedido>
	<pedido>
		<id>41</id>
		<id_cliente>17</id_cliente>
		<fecha>12/13/2018</fecha>
	</pedido>
	<pedido>
		<id>42</id>
		<id_cliente>18</id_cliente>
		<fecha>02/28/2019</fecha>
	</pedido>
	<pedido>
		<id>43</id>
		<id_cliente>20</id_cliente>
		<fecha>02/21/2020</fecha>
	</pedido>
	<pedido>
		<id>44</id>
		<id_cliente>12</id_cliente>
		<fecha>02/25/2019</fecha>
	</pedido>
	<pedido>
		<id>45</id>
		<id_cliente>19</id_cliente>
		<fecha>07/09/2018</fecha>
	</pedido>
	<pedido>
		<id>46</id>
		<id_cliente>13</id_cliente>
		<fecha>07/09/2018</fecha>
	</pedido>
	<pedido>
		<id>47</id>
		<id_cliente>1</id_cliente>
		<fecha>09/20/2018</fecha>
	</pedido>
	<pedido>
		<id>48</id>
		<id_cliente>18</id_cliente>
		<fecha>06/14/2018</fecha>
	</pedido>
	<pedido>
		<id>49</id>
		<id_cliente>19</id_cliente>
		<fecha>08/14/2019</fecha>
	</pedido>
	<pedido>
		<id>50</id>
		<id_cliente>12</id_cliente>
		<fecha>03/19/2020</fecha>
	</pedido>
	<pedido>
		<id>51</id>
		<id_cliente>25</id_cliente>
		<fecha>05/18/2020</fecha>
	</pedido>
	<pedido>
		<id>52</id>
		<id_cliente>5</id_cliente>
		<fecha>10/09/2019</fecha>
	</pedido>
	<pedido>
		<id>53</id>
		<id_cliente>4</id_cliente>
		<fecha>08/15/2019</fecha>
	</pedido>
	<pedido>
		<id>54</id>
		<id_cliente>2</id_cliente>
		<fecha>07/28/2018</fecha>
	</pedido>
	<pedido>
		<id>55</id>
		<id_cliente>19</id_cliente>
		<fecha>01/17/2020</fecha>
	</pedido>
	<pedido>
		<id>56</id>
		<id_cliente>7</id_cliente>
		<fecha>04/09/2020</fecha>
	</pedido>
	<pedido>
		<id>57</id>
		<id_cliente>19</id_cliente>
		<fecha>10/12/2018</fecha>
	</pedido>
	<pedido>
		<id>58</id>
		<id_cliente>17</id_cliente>
		<fecha>07/09/2018</fecha>
	</pedido>
	<pedido>
		<id>59</id>
		<id_cliente>16</id_cliente>
		<fecha>03/27/2019</fecha>
	</pedido>
	<pedido>
		<id>60</id>
		<id_cliente>23</id_cliente>
		<fecha>10/06/2018</fecha>
	</pedido>
	<pedido>
		<id>61</id>
		<id_cliente>22</id_cliente>
		<fecha>05/02/2019</fecha>
	</pedido>
	<pedido>
		<id>62</id>
		<id_cliente>23</id_cliente>
		<fecha>02/05/2020</fecha>
	</pedido>
	<pedido>
		<id>63</id>
		<id_cliente>2</id_cliente>
		<fecha>08/08/2019</fecha>
	</pedido>
	<pedido>
		<id>64</id>
		<id_cliente>18</id_cliente>
		<fecha>04/24/2020</fecha>
	</pedido>
	<pedido>
		<id>65</id>
		<id_cliente>17</id_cliente>
		<fecha>01/03/2019</fecha>
	</pedido>
	<pedido>
		<id>66</id>
		<id_cliente>16</id_cliente>
		<fecha>06/22/2018</fecha>
	</pedido>
	<pedido>
		<id>67</id>
		<id_cliente>23</id_cliente>
		<fecha>04/19/2020</fecha>
	</pedido>
	<pedido>
		<id>68</id>
		<id_cliente>25</id_cliente>
		<fecha>07/19/2018</fecha>
	</pedido>
	<pedido>
		<id>69</id>
		<id_cliente>7</id_cliente>
		<fecha>05/13/2020</fecha>
	</pedido>
	<pedido>
		<id>70</id>
		<id_cliente>17</id_cliente>
		<fecha>11/16/2018</fecha>
	</pedido>
	<pedido>
		<id>71</id>
		<id_cliente>2</id_cliente>
		<fecha>09/30/2018</fecha>
	</pedido>
	<pedido>
		<id>72</id>
		<id_cliente>17</id_cliente>
		<fecha>03/19/2020</fecha>
	</pedido>
	<pedido>
		<id>73</id>
		<id_cliente>19</id_cliente>
		<fecha>05/07/2019</fecha>
	</pedido>
	<pedido>
		<id>74</id>
		<id_cliente>2</id_cliente>
		<fecha>02/04/2020</fecha>
	</pedido>
	<pedido>
		<id>75</id>
		<id_cliente>21</id_cliente>
		<fecha>06/06/2019</fecha>
	</pedido>
	<pedido>
		<id>76</id>
		<id_cliente>12</id_cliente>
		<fecha>12/13/2018</fecha>
	</pedido>
	<pedido>
		<id>77</id>
		<id_cliente>19</id_cliente>
		<fecha>06/02/2020</fecha>
	</pedido>
	<pedido>
		<id>78</id>
		<id_cliente>3</id_cliente>
		<fecha>09/16/2019</fecha>
	</pedido>
	<pedido>
		<id>79</id>
		<id_cliente>12</id_cliente>
		<fecha>09/21/2018</fecha>
	</pedido>
	<pedido>
		<id>80</id>
		<id_cliente>14</id_cliente>
		<fecha>04/18/2020</fecha>
	</pedido>
	<pedido>
		<id>81</id>
		<id_cliente>10</id_cliente>
		<fecha>10/24/2019</fecha>
	</pedido>
	<pedido>
		<id>82</id>
		<id_cliente>5</id_cliente>
		<fecha>02/09/2019</fecha>
	</pedido>
	<pedido>
		<id>83</id>
		<id_cliente>16</id_cliente>
		<fecha>08/11/2018</fecha>
	</pedido>
	<pedido>
		<id>84</id>
		<id_cliente>2</id_cliente>
		<fecha>02/10/2020</fecha>
	</pedido>
	<pedido>
		<id>85</id>
		<id_cliente>8</id_cliente>
		<fecha>07/25/2018</fecha>
	</pedido>
	<pedido>
		<id>86</id>
		<id_cliente>13</id_cliente>
		<fecha>10/11/2019</fecha>
	</pedido>
	<pedido>
		<id>87</id>
		<id_cliente>8</id_cliente>
		<fecha>08/08/2019</fecha>
	</pedido>
	<pedido>
		<id>88</id>
		<id_cliente>4</id_cliente>
		<fecha>12/28/2019</fecha>
	</pedido>
	<pedido>
		<id>89</id>
		<id_cliente>3</id_cliente>
		<fecha>03/18/2020</fecha>
	</pedido>
	<pedido>
		<id>90</id>
		<id_cliente>25</id_cliente>
		<fecha>05/03/2019</fecha>
	</pedido>
	<pedido>
		<id>91</id>
		<id_cliente>22</id_cliente>
		<fecha>10/14/2018</fecha>
	</pedido>
	<pedido>
		<id>92</id>
		<id_cliente>25</id_cliente>
		<fecha>11/06/2019</fecha>
	</pedido>
	<pedido>
		<id>93</id>
		<id_cliente>25</id_cliente>
		<fecha>12/14/2019</fecha>
	</pedido>
	<pedido>
		<id>94</id>
		<id_cliente>22</id_cliente>
		<fecha>05/17/2019</fecha>
	</pedido>
	<pedido>
		<id>95</id>
		<id_cliente>22</id_cliente>
		<fecha>01/16/2019</fecha>
	</pedido>
	<pedido>
		<id>96</id>
		<id_cliente>8</id_cliente>
		<fecha>11/07/2018</fecha>
	</pedido>
	<pedido>
		<id>97</id>
		<id_cliente>13</id_cliente>
		<fecha>05/07/2020</fecha>
	</pedido>
	<pedido>
		<id>98</id>
		<id_cliente>8</id_cliente>
		<fecha>09/01/2019</fecha>
	</pedido>
	<pedido>
		<id>99</id>
		<id_cliente>9</id_cliente>
		<fecha>02/25/2019</fecha>
	</pedido>
	<pedido>
		<id>100</id>
		<id_cliente>9</id_cliente>
		<fecha>10/28/2018</fecha>
	</pedido>
</pedidos>